README.md
setup.py
cloudhealth/__init__.py
cloudhealth_cli.egg-info/PKG-INFO
cloudhealth_cli.egg-info/SOURCES.txt
cloudhealth_cli.egg-info/dependency_links.txt
cloudhealth_cli.egg-info/top_level.txt