Metadata-Version: 2.1
Name: cloudhealth-cli
Version: 0.0.1
Summary: CloudHealthi CLI
Home-page: https://github.com/awslabs/cloudhealth-cli
Author: troylar
Author-email: troylar@pm.me
License: Apache-2.0
Keywords: cloudhealth
Platform: UNKNOWN
Classifier: Development Status :: 5 - Production/Stable
Classifier: Topic :: Utilities
Classifier: License :: OSI Approved :: Apache Software License
